CSSA_TEST/__init__.py
CSSA_TEST/add_one.py
CSSA_TEST/test_module.py
CSSA_TEST-0.1.2.dist-info/METADATA
CSSA_TEST-0.1.2.dist-info/WHEEL
CSSA_TEST-0.1.2.dist-info/top_level.txt
CSSA_TEST-0.1.2.dist-info/RECORD
