Metadata-Version: 2.1
Name: CSSA_TEST
Version: 0.1.2
Summary: cut the verdict into different part
Home-page: https://github.com/
Author: CSSA
Author-email: 
Classifier: Programming Language :: Python :: 3
Classifier: License :: OSI Approved :: MIT License
Classifier: Operating System :: OS Independent
Requires-Python: >=3.6
